{"nodes": [{"id": "c_work_safenetai7_mlmodel_app_routers_email_scan_py", "label": "email_scan.py", "file_type": "code", "source_file": "C:\\Work\\safenetai7\\mlmodel\\app\\routers\\email_scan.py", "source_location": "L1"}, {"id": "email_scan_count_matches", "label": "count_matches()", "file_type": "code", "source_file": "C:\\Work\\safenetai7\\mlmodel\\app\\routers\\email_scan.py", "source_location": "L92"}, {"id": "email_scan_has_fee_demand", "label": "has_fee_demand()", "file_type": "code", "source_file": "C:\\Work\\safenetai7\\mlmodel\\app\\routers\\email_scan.py", "source_location": "L97"}, {"id": "email_scan_extract_features", "label": "extract_features()", "file_type": "code", "source_file": "C:\\Work\\safenetai7\\mlmodel\\app\\routers\\email_scan.py", "source_location": "L101"}, {"id": "email_scan_get_red_flags", "label": "get_red_flags()", "file_type": "code", "source_file": "C:\\Work\\safenetai7\\mlmodel\\app\\routers\\email_scan.py", "source_location": "L126"}, {"id": "email_scan_clean_text_for_offer", "label": "clean_text_for_offer()", "file_type": "code", "source_file": "C:\\Work\\safenetai7\\mlmodel\\app\\routers\\email_scan.py", "source_location": "L147"}, {"id": "email_scan_emailrequest", "label": "EmailRequest", "file_type": "code", "source_file": "C:\\Work\\safenetai7\\mlmodel\\app\\routers\\email_scan.py", "source_location": "L158"}, {"id": "basemodel", "label": "BaseModel", "file_type": "code", "source_file": "", "source_location": ""}, {"id": "email_scan_emailprediction", "label": "EmailPrediction", "file_type": "code", "source_file": "C:\\Work\\safenetai7\\mlmodel\\app\\routers\\email_scan.py", "source_location": "L162"}, {"id": "email_scan_predict_email", "label": "predict_email()", "file_type": "code", "source_file": "C:\\Work\\safenetai7\\mlmodel\\app\\routers\\email_scan.py", "source_location": "L169"}], "edges": [{"source": "c_work_safenetai7_mlmodel_app_routers_email_scan_py", "target": "fastapi", "relation": "imports_from", "confidence": "EXTRACTED", "source_file": "C:\\Work\\safenetai7\\mlmodel\\app\\routers\\email_scan.py", "source_location": "L2", "weight": 1.0}, {"source": "c_work_safenetai7_mlmodel_app_routers_email_scan_py", "target": "pydantic", "relation": "imports_from", "confidence": "EXTRACTED", "source_file": "C:\\Work\\safenetai7\\mlmodel\\app\\routers\\email_scan.py", "source_location": "L3", "weight": 1.0}, {"source": "c_work_safenetai7_mlmodel_app_routers_email_scan_py", "target": "joblib", "relation": "imports", "confidence": "EXTRACTED", "source_file": "C:\\Work\\safenetai7\\mlmodel\\app\\routers\\email_scan.py", "source_location": "L4", "weight": 1.0}, {"source": "c_work_safenetai7_mlmodel_app_routers_email_scan_py", "target": "json", "relation": "imports", "confidence": "EXTRACTED", "source_file": "C:\\Work\\safenetai7\\mlmodel\\app\\routers\\email_scan.py", "source_location": "L5", "weight": 1.0}, {"source": "c_work_safenetai7_mlmodel_app_routers_email_scan_py", "target": "os", "relation": "imports", "confidence": "EXTRACTED", "source_file": "C:\\Work\\safenetai7\\mlmodel\\app\\routers\\email_scan.py", "source_location": "L6", "weight": 1.0}, {"source": "c_work_safenetai7_mlmodel_app_routers_email_scan_py", "target": "re", "relation": "imports", "confidence": "EXTRACTED", "source_file": "C:\\Work\\safenetai7\\mlmodel\\app\\routers\\email_scan.py", "source_location": "L7", "weight": 1.0}, {"source": "c_work_safenetai7_mlmodel_app_routers_email_scan_py", "target": "pandas", "relation": "imports", "confidence": "EXTRACTED", "source_file": "C:\\Work\\safenetai7\\mlmodel\\app\\routers\\email_scan.py", "source_location": "L8", "weight": 1.0}, {"source": "c_work_safenetai7_mlmodel_app_routers_email_scan_py", "target": "numpy", "relation": "imports", "confidence": "EXTRACTED", "source_file": "C:\\Work\\safenetai7\\mlmodel\\app\\routers\\email_scan.py", "source_location": "L9", "weight": 1.0}, {"source": "c_work_safenetai7_mlmodel_app_routers_email_scan_py", "target": "scipy_sparse", "relation": "imports_from", "confidence": "EXTRACTED", "source_file": "C:\\Work\\safenetai7\\mlmodel\\app\\routers\\email_scan.py", "source_location": "L10", "weight": 1.0}, {"source": "c_work_safenetai7_mlmodel_app_routers_email_scan_py", "target": "typing", "relation": "imports_from", "confidence": "EXTRACTED", "source_file": "C:\\Work\\safenetai7\\mlmodel\\app\\routers\\email_scan.py", "source_location": "L11", "weight": 1.0}, {"source": "c_work_safenetai7_mlmodel_app_routers_email_scan_py", "target": "email_scan_count_matches", "relation": "contains", "confidence": "EXTRACTED", "source_file": "C:\\Work\\safenetai7\\mlmodel\\app\\routers\\email_scan.py", "source_location": "L92", "weight": 1.0}, {"source": "c_work_safenetai7_mlmodel_app_routers_email_scan_py", "target": "email_scan_has_fee_demand", "relation": "contains", "confidence": "EXTRACTED", "source_file": "C:\\Work\\safenetai7\\mlmodel\\app\\routers\\email_scan.py", "source_location": "L97", "weight": 1.0}, {"source": "c_work_safenetai7_mlmodel_app_routers_email_scan_py", "target": "email_scan_extract_features", "relation": "contains", "confidence": "EXTRACTED", "source_file": "C:\\Work\\safenetai7\\mlmodel\\app\\routers\\email_scan.py", "source_location": "L101", "weight": 1.0}, {"source": "c_work_safenetai7_mlmodel_app_routers_email_scan_py", "target": "email_scan_get_red_flags", "relation": "contains", "confidence": "EXTRACTED", "source_file": "C:\\Work\\safenetai7\\mlmodel\\app\\routers\\email_scan.py", "source_location": "L126", "weight": 1.0}, {"source": "c_work_safenetai7_mlmodel_app_routers_email_scan_py", "target": "email_scan_clean_text_for_offer", "relation": "contains", "confidence": "EXTRACTED", "source_file": "C:\\Work\\safenetai7\\mlmodel\\app\\routers\\email_scan.py", "source_location": "L147", "weight": 1.0}, {"source": "c_work_safenetai7_mlmodel_app_routers_email_scan_py", "target": "email_scan_emailrequest", "relation": "contains", "confidence": "EXTRACTED", "source_file": "C:\\Work\\safenetai7\\mlmodel\\app\\routers\\email_scan.py", "source_location": "L158", "weight": 1.0}, {"source": "email_scan_emailrequest", "target": "basemodel", "relation": "inherits", "confidence": "EXTRACTED", "source_file": "C:\\Work\\safenetai7\\mlmodel\\app\\routers\\email_scan.py", "source_location": "L158", "weight": 1.0}, {"source": "c_work_safenetai7_mlmodel_app_routers_email_scan_py", "target": "email_scan_emailprediction", "relation": "contains", "confidence": "EXTRACTED", "source_file": "C:\\Work\\safenetai7\\mlmodel\\app\\routers\\email_scan.py", "source_location": "L162", "weight": 1.0}, {"source": "email_scan_emailprediction", "target": "basemodel", "relation": "inherits", "confidence": "EXTRACTED", "source_file": "C:\\Work\\safenetai7\\mlmodel\\app\\routers\\email_scan.py", "source_location": "L162", "weight": 1.0}, {"source": "c_work_safenetai7_mlmodel_app_routers_email_scan_py", "target": "email_scan_predict_email", "relation": "contains", "confidence": "EXTRACTED", "source_file": "C:\\Work\\safenetai7\\mlmodel\\app\\routers\\email_scan.py", "source_location": "L169", "weight": 1.0}, {"source": "email_scan_has_fee_demand", "target": "email_scan_count_matches", "relation": "calls", "confidence": "EXTRACTED", "source_file": "C:\\Work\\safenetai7\\mlmodel\\app\\routers\\email_scan.py", "source_location": "L98", "weight": 1.0}, {"source": "email_scan_extract_features", "target": "email_scan_has_fee_demand", "relation": "calls", "confidence": "EXTRACTED", "source_file": "C:\\Work\\safenetai7\\mlmodel\\app\\routers\\email_scan.py", "source_location": "L103", "weight": 1.0}, {"source": "email_scan_extract_features", "target": "email_scan_count_matches", "relation": "calls", "confidence": "EXTRACTED", "source_file": "C:\\Work\\safenetai7\\mlmodel\\app\\routers\\email_scan.py", "source_location": "L104", "weight": 1.0}, {"source": "email_scan_get_red_flags", "target": "email_scan_has_fee_demand", "relation": "calls", "confidence": "EXTRACTED", "source_file": "C:\\Work\\safenetai7\\mlmodel\\app\\routers\\email_scan.py", "source_location": "L128", "weight": 1.0}, {"source": "email_scan_get_red_flags", "target": "email_scan_count_matches", "relation": "calls", "confidence": "EXTRACTED", "source_file": "C:\\Work\\safenetai7\\mlmodel\\app\\routers\\email_scan.py", "source_location": "L130", "weight": 1.0}, {"source": "email_scan_predict_email", "target": "email_scan_extract_features", "relation": "calls", "confidence": "EXTRACTED", "source_file": "C:\\Work\\safenetai7\\mlmodel\\app\\routers\\email_scan.py", "source_location": "L171", "weight": 1.0}, {"source": "email_scan_predict_email", "target": "email_scan_clean_text_for_offer", "relation": "calls", "confidence": "EXTRACTED", "source_file": "C:\\Work\\safenetai7\\mlmodel\\app\\routers\\email_scan.py", "source_location": "L173", "weight": 1.0}, {"source": "email_scan_predict_email", "target": "email_scan_get_red_flags", "relation": "calls", "confidence": "EXTRACTED", "source_file": "C:\\Work\\safenetai7\\mlmodel\\app\\routers\\email_scan.py", "source_location": "L179", "weight": 1.0}], "raw_calls": [{"caller_nid": "email_scan_count_matches", "callee": "lower", "source_file": "C:\\Work\\safenetai7\\mlmodel\\app\\routers\\email_scan.py", "source_location": "L93"}, {"caller_nid": "email_scan_count_matches", "callee": "sum", "source_file": "C:\\Work\\safenetai7\\mlmodel\\app\\routers\\email_scan.py", "source_location": "L94"}, {"caller_nid": "email_scan_count_matches", "callee": "search", "source_file": "C:\\Work\\safenetai7\\mlmodel\\app\\routers\\email_scan.py", "source_location": "L94"}, {"caller_nid": "email_scan_extract_features", "callee": "min", "source_file": "C:\\Work\\safenetai7\\mlmodel\\app\\routers\\email_scan.py", "source_location": "L112"}, {"caller_nid": "email_scan_extract_features", "callee": "len", "source_file": "C:\\Work\\safenetai7\\mlmodel\\app\\routers\\email_scan.py", "source_location": "L112"}, {"caller_nid": "email_scan_extract_features", "callee": "min", "source_file": "C:\\Work\\safenetai7\\mlmodel\\app\\routers\\email_scan.py", "source_location": "L113"}, {"caller_nid": "email_scan_extract_features", "callee": "len", "source_file": "C:\\Work\\safenetai7\\mlmodel\\app\\routers\\email_scan.py", "source_location": "L113"}, {"caller_nid": "email_scan_extract_features", "callee": "split", "source_file": "C:\\Work\\safenetai7\\mlmodel\\app\\routers\\email_scan.py", "source_location": "L113"}, {"caller_nid": "email_scan_extract_features", "callee": "search", "source_file": "C:\\Work\\safenetai7\\mlmodel\\app\\routers\\email_scan.py", "source_location": "L114"}, {"caller_nid": "email_scan_extract_features", "callee": "min", "source_file": "C:\\Work\\safenetai7\\mlmodel\\app\\routers\\email_scan.py", "source_location": "L115"}, {"caller_nid": "email_scan_extract_features", "callee": "count", "source_file": "C:\\Work\\safenetai7\\mlmodel\\app\\routers\\email_scan.py", "source_location": "L115"}, {"caller_nid": "email_scan_extract_features", "callee": "round", "source_file": "C:\\Work\\safenetai7\\mlmodel\\app\\routers\\email_scan.py", "source_location": "L116"}, {"caller_nid": "email_scan_extract_features", "callee": "sum", "source_file": "C:\\Work\\safenetai7\\mlmodel\\app\\routers\\email_scan.py", "source_location": "L116"}, {"caller_nid": "email_scan_extract_features", "callee": "isupper", "source_file": "C:\\Work\\safenetai7\\mlmodel\\app\\routers\\email_scan.py", "source_location": "L116"}, {"caller_nid": "email_scan_extract_features", "callee": "max", "source_file": "C:\\Work\\safenetai7\\mlmodel\\app\\routers\\email_scan.py", "source_location": "L116"}, {"caller_nid": "email_scan_extract_features", "callee": "len", "source_file": "C:\\Work\\safenetai7\\mlmodel\\app\\routers\\email_scan.py", "source_location": "L116"}, {"caller_nid": "email_scan_extract_features", "callee": "len", "source_file": "C:\\Work\\safenetai7\\mlmodel\\app\\routers\\email_scan.py", "source_location": "L117"}, {"caller_nid": "email_scan_extract_features", "callee": "findall", "source_file": "C:\\Work\\safenetai7\\mlmodel\\app\\routers\\email_scan.py", "source_location": "L117"}, {"caller_nid": "email_scan_extract_features", "callee": "len", "source_file": "C:\\Work\\safenetai7\\mlmodel\\app\\routers\\email_scan.py", "source_location": "L118"}, {"caller_nid": "email_scan_extract_features", "callee": "findall", "source_file": "C:\\Work\\safenetai7\\mlmodel\\app\\routers\\email_scan.py", "source_location": "L118"}, {"caller_nid": "email_scan_get_red_flags", "callee": "append", "source_file": "C:\\Work\\safenetai7\\mlmodel\\app\\routers\\email_scan.py", "source_location": "L129"}, {"caller_nid": "email_scan_get_red_flags", "callee": "append", "source_file": "C:\\Work\\safenetai7\\mlmodel\\app\\routers\\email_scan.py", "source_location": "L131"}, {"caller_nid": "email_scan_get_red_flags", "callee": "append", "source_file": "C:\\Work\\safenetai7\\mlmodel\\app\\routers\\email_scan.py", "source_location": "L133"}, {"caller_nid": "email_scan_get_red_flags", "callee": "append", "source_file": "C:\\Work\\safenetai7\\mlmodel\\app\\routers\\email_scan.py", "source_location": "L135"}, {"caller_nid": "email_scan_get_red_flags", "callee": "append", "source_file": "C:\\Work\\safenetai7\\mlmodel\\app\\routers\\email_scan.py", "source_location": "L137"}, {"caller_nid": "email_scan_get_red_flags", "callee": "append", "source_file": "C:\\Work\\safenetai7\\mlmodel\\app\\routers\\email_scan.py", "source_location": "L139"}, {"caller_nid": "email_scan_get_red_flags", "callee": "append", "source_file": "C:\\Work\\safenetai7\\mlmodel\\app\\routers\\email_scan.py", "source_location": "L141"}, {"caller_nid": "email_scan_get_red_flags", "callee": "search", "source_file": "C:\\Work\\safenetai7\\mlmodel\\app\\routers\\email_scan.py", "source_location": "L142"}, {"caller_nid": "email_scan_get_red_flags", "callee": "len", "source_file": "C:\\Work\\safenetai7\\mlmodel\\app\\routers\\email_scan.py", "source_location": "L142"}, {"caller_nid": "email_scan_get_red_flags", "callee": "append", "source_file": "C:\\Work\\safenetai7\\mlmodel\\app\\routers\\email_scan.py", "source_location": "L143"}, {"caller_nid": "email_scan_clean_text_for_offer", "callee": "lower", "source_file": "C:\\Work\\safenetai7\\mlmodel\\app\\routers\\email_scan.py", "source_location": "L148"}, {"caller_nid": "email_scan_clean_text_for_offer", "callee": "str", "source_file": "C:\\Work\\safenetai7\\mlmodel\\app\\routers\\email_scan.py", "source_location": "L148"}, {"caller_nid": "email_scan_clean_text_for_offer", "callee": "sub", "source_file": "C:\\Work\\safenetai7\\mlmodel\\app\\routers\\email_scan.py", "source_location": "L149"}, {"caller_nid": "email_scan_clean_text_for_offer", "callee": "sub", "source_file": "C:\\Work\\safenetai7\\mlmodel\\app\\routers\\email_scan.py", "source_location": "L150"}, {"caller_nid": "email_scan_clean_text_for_offer", "callee": "sub", "source_file": "C:\\Work\\safenetai7\\mlmodel\\app\\routers\\email_scan.py", "source_location": "L151"}, {"caller_nid": "email_scan_clean_text_for_offer", "callee": "sub", "source_file": "C:\\Work\\safenetai7\\mlmodel\\app\\routers\\email_scan.py", "source_location": "L152"}, {"caller_nid": "email_scan_clean_text_for_offer", "callee": "sub", "source_file": "C:\\Work\\safenetai7\\mlmodel\\app\\routers\\email_scan.py", "source_location": "L153"}, {"caller_nid": "email_scan_clean_text_for_offer", "callee": "strip", "source_file": "C:\\Work\\safenetai7\\mlmodel\\app\\routers\\email_scan.py", "source_location": "L154"}, {"caller_nid": "email_scan_clean_text_for_offer", "callee": "sub", "source_file": "C:\\Work\\safenetai7\\mlmodel\\app\\routers\\email_scan.py", "source_location": "L154"}, {"caller_nid": "email_scan_predict_email", "callee": "csr_matrix", "source_file": "C:\\Work\\safenetai7\\mlmodel\\app\\routers\\email_scan.py", "source_location": "L172"}, {"caller_nid": "email_scan_predict_email", "callee": "DataFrame", "source_file": "C:\\Work\\safenetai7\\mlmodel\\app\\routers\\email_scan.py", "source_location": "L172"}, {"caller_nid": "email_scan_predict_email", "callee": "transform", "source_file": "C:\\Work\\safenetai7\\mlmodel\\app\\routers\\email_scan.py", "source_location": "L173"}, {"caller_nid": "email_scan_predict_email", "callee": "hstack", "source_file": "C:\\Work\\safenetai7\\mlmodel\\app\\routers\\email_scan.py", "source_location": "L174"}, {"caller_nid": "email_scan_predict_email", "callee": "predict", "source_file": "C:\\Work\\safenetai7\\mlmodel\\app\\routers\\email_scan.py", "source_location": "L176"}, {"caller_nid": "email_scan_predict_email", "callee": "predict_proba", "source_file": "C:\\Work\\safenetai7\\mlmodel\\app\\routers\\email_scan.py", "source_location": "L177"}, {"caller_nid": "email_scan_predict_email", "callee": "round", "source_file": "C:\\Work\\safenetai7\\mlmodel\\app\\routers\\email_scan.py", "source_location": "L183"}]}